MRISnapshot/__init__.py
MRISnapshot/create_report.py
MRISnapshot/prep_data.py
MRISnapshot/js_templates/load_back.js
MRISnapshot/js_templates/misc_func.js
MRISnapshot/js_templates/save_qcform.js
MRISnapshot/js_templates/shortcut.js
MRISnapshot/utils/__init__.py
MRISnapshot/utils/html_utils.py
MRISnapshot/utils/img_overlays.py
MRISnapshot/utils/misc_utils.py
MRISnapshot/utils/mylogger.py
mrisnapshot-0.0.5.dev0.data/data/load_back.js
mrisnapshot-0.0.5.dev0.data/data/misc_func.js
mrisnapshot-0.0.5.dev0.data/data/save_qcform.js
mrisnapshot-0.0.5.dev0.data/data/shortcut.js
mrisnapshot-0.0.5.dev0.dist-info/licenses/LICENSE
mrisnapshot-0.0.5.dev0.dist-info/METADATA
mrisnapshot-0.0.5.dev0.dist-info/WHEEL
mrisnapshot-0.0.5.dev0.dist-info/entry_points.txt
mrisnapshot-0.0.5.dev0.dist-info/top_level.txt
mrisnapshot-0.0.5.dev0.dist-info/RECORD
