Metadata-Version: 2.4
Name: mrisnapshot
Version: 0.0.5.dev0
Summary: QC tool for verification of datasets with MRI images and derived maps
Home-page: https://github.com/CBICA/MRISnapshot
Author: Guray Erus
Author-email: guray.erus@pennmedicine.upenn.edu
License: MIT
Classifier: Intended Audience :: Science/Research
Classifier: Programming Language :: Python
Classifier: Topic :: Scientific/Engineering
Classifier: Operating System :: Unix
License-File: LICENSE
Requires-Dist: numpy
Requires-Dist: pandas
Requires-Dist: nibabel
Requires-Dist: pillow
Requires-Dist: scipy
Requires-Dist: matplotlib
Dynamic: author
Dynamic: author-email
Dynamic: classifier
Dynamic: description
Dynamic: description-content-type
Dynamic: home-page
Dynamic: license
Dynamic: license-file
Dynamic: requires-dist
Dynamic: summary
